README.txt
setup.cfg
setup.py
Products/__init__.py
Products.ATMediaPage.egg-info/PKG-INFO
Products.ATMediaPage.egg-info/SOURCES.txt
Products.ATMediaPage.egg-info/dependency_links.txt
Products.ATMediaPage.egg-info/entry_points.txt
Products.ATMediaPage.egg-info/namespace_packages.txt
Products.ATMediaPage.egg-info/not-zip-safe
Products.ATMediaPage.egg-info/paster_plugins.txt
Products.ATMediaPage.egg-info/requires.txt
Products.ATMediaPage.egg-info/top_level.txt
Products/ATMediaPage/MediaPage.py
Products/ATMediaPage/__init__.py
Products/ATMediaPage/config.py
Products/ATMediaPage/configure.zcml
Products/ATMediaPage/exportimport.py
Products/ATMediaPage/migration.py
Products/ATMediaPage/setuphandlers.py
Products/ATMediaPage/skins.zcml
Products/ATMediaPage/browser/__init__.py
Products/ATMediaPage/browser/configure.zcml
Products/ATMediaPage/browser/mediapage.py
Products/ATMediaPage/browser/templates/mp_banner_bottom.pt
Products/ATMediaPage/browser/templates/mp_banner_left.pt
Products/ATMediaPage/browser/templates/mp_banner_left_old.pt
Products/ATMediaPage/browser/templates/mp_banner_right.pt
Products/ATMediaPage/browser/templates/mp_banner_right_old.pt
Products/ATMediaPage/browser/templates/mp_default_right.pt
Products/ATMediaPage/browser/templates/mp_default_right_old.pt
Products/ATMediaPage/content/__init__.py
Products/ATMediaPage/content/configure.zcml
Products/ATMediaPage/content/mediapage.py
Products/ATMediaPage/i18n/plone-de.po
Products/ATMediaPage/interfaces/__init__.py
Products/ATMediaPage/interfaces/browserlayer.py
Products/ATMediaPage/interfaces/mediapage.py
Products/ATMediaPage/portlets/__init__.py
Products/ATMediaPage/portlets/configure.zcml
Products/ATMediaPage/profiles/default/Products.ATMediaPage.txt
Products/ATMediaPage/profiles/default/browserlayer.xml
Products/ATMediaPage/profiles/default/cssregistry.xml
Products/ATMediaPage/profiles/default/diff_tool.xml
Products/ATMediaPage/profiles/default/factorytool.xml
Products/ATMediaPage/profiles/default/jsregistry.xml
Products/ATMediaPage/profiles/default/metadata.xml
Products/ATMediaPage/profiles/default/portlets.xml
Products/ATMediaPage/profiles/default/propertiestool.xml
Products/ATMediaPage/profiles/default/rolemap.xml
Products/ATMediaPage/profiles/default/skins.xml
Products/ATMediaPage/profiles/default/tinymce.xml
Products/ATMediaPage/profiles/default/types.xml
