Metadata-Version: 1.0
Name: Products.ATMediaPage
Version: 0.2.2
Summary: Simple and easy to use Plone page with predefined layouts.
Home-page: http://plone.org/products/atmediapage
Author: Maik Derstappen
Author-email: maik.derstappen@inqbus.de
License: GPL
Keywords: Zope CMF Plone Images Layout Document Article
Platform: UNKNOWN
Classifier: Framework :: Plone
Classifier: Programming Language :: Python
